agent_pilot/__init__.py
agent_pilot/config.py
agent_pilot/consumer.py
agent_pilot/context.py
agent_pilot/event_queue.py
agent_pilot/http_client.py
agent_pilot/models.py
agent_pilot/openai_utils.py
agent_pilot/parsers.py
agent_pilot/prompt.py
agent_pilot/tracking.py
agent_pilot/utils.py
agent_pilot/volcengine_utils.py
agent_pilot/eval/__init__.py
agent_pilot/eval/api.py
agent_pilot/eval/eval_client.py
agent_pilot/eval/models.py
agent_pilot/optimize/__init__.py
agent_pilot/optimize/models.py
agent_pilot/optimize/optimize_client.py
agent_pilot/optimize/optimize_job.py
agent_pilot/pe/__init__.py
agent_pilot/pe/api.py
agent_pilot/pe/models.py
agent_pilot/pe/utils.py
agent_pilot_sdk-0.1.3.dist-info/METADATA
agent_pilot_sdk-0.1.3.dist-info/WHEEL
agent_pilot_sdk-0.1.3.dist-info/licenses/LICENSE.txt
agent_pilot_sdk-0.1.3.dist-info/RECORD
