Metadata-Version: 2.4
Name: agent-pilot-sdk
Version: 0.1.3
Summary: An SDK for LLM tracing and more.
Author-email: Jinlai Xu <jinlai.xu@bytedance.com>
License: 
License-File: LICENSE.txt
Classifier: Development Status :: 3 - Alpha
Classifier: Intended Audience :: Developers
Classifier: Programming Language :: Python :: 3
Classifier: Programming Language :: Python :: 3.9
Classifier: Programming Language :: Python :: 3.10
Classifier: Programming Language :: Python :: 3.11
Requires-Python: >=3.9
Requires-Dist: chevron>=0.14.0
Requires-Dist: jsonpickle>=3.4.2
Requires-Dist: loguru>=0.7.0
Requires-Dist: openpyxl>=3.1.5
Requires-Dist: pydantic>=2.0.0
Requires-Dist: requests>=2.29.0
Requires-Dist: uv>=0.5.23
Requires-Dist: volcengine-python-sdk[ark]>=2.0.1
Provides-Extra: dev
Requires-Dist: mypy>=1.3.0; extra == 'dev'
Requires-Dist: pre-commit>=4.2.0; extra == 'dev'
Requires-Dist: pytest-cov>=4.1.0; extra == 'dev'
Requires-Dist: pytest>=7.3.1; extra == 'dev'
Requires-Dist: ruff>=0.9.10; extra == 'dev'
Requires-Dist: types-requests>=2.29; extra == 'dev'
